odoo/addons/repair_refurbish_repair_stock_move/README.rst
odoo/addons/repair_refurbish_repair_stock_move/__init__.py
odoo/addons/repair_refurbish_repair_stock_move/__manifest__.py
odoo/addons/repair_refurbish_repair_stock_move/i18n/es.po
odoo/addons/repair_refurbish_repair_stock_move/i18n/it.po
odoo/addons/repair_refurbish_repair_stock_move/i18n/repair_refurbish_repair_stock_move.pot
odoo/addons/repair_refurbish_repair_stock_move/models/__init__.py
odoo/addons/repair_refurbish_repair_stock_move/models/repair_order.py
odoo/addons/repair_refurbish_repair_stock_move/readme/CONTRIBUTORS.rst
odoo/addons/repair_refurbish_repair_stock_move/readme/DESCRIPTION.rst
odoo/addons/repair_refurbish_repair_stock_move/static/description/icon.png
odoo/addons/repair_refurbish_repair_stock_move/static/description/index.html
odoo14_addon_repair_refurbish_repair_stock_move-14.0.1.0.1.dev8.dist-info/METADATA
odoo14_addon_repair_refurbish_repair_stock_move-14.0.1.0.1.dev8.dist-info/WHEEL
odoo14_addon_repair_refurbish_repair_stock_move-14.0.1.0.1.dev8.dist-info/top_level.txt
odoo14_addon_repair_refurbish_repair_stock_move-14.0.1.0.1.dev8.dist-info/RECORD
