Metadata-Version: 2.1
Name: odoo14-addon-repair-refurbish-repair-stock-move
Version: 14.0.1.0.1.dev8
Summary: Use refurbish and repair stock moves together
Home-page: https://github.com/OCA/manufacture
Author: ForgeFlow S.L., Odoo Community Association (OCA)
Author-email: support@odoo-community.org
License: AGPL-3
Platform: UNKNOWN
Classifier: Programming Language :: Python
Classifier: Framework :: Odoo
Classifier: Framework :: Odoo :: 14.0
Classifier: License :: OSI Approved :: GNU Affero General Public License v3
Classifier: Development Status :: 3 - Alpha
Requires-Python: >=3.6
Requires-Dist: odoo14-addon-repair-refurbish
Requires-Dist: odoo14-addon-repair-stock-move
Requires-Dist: odoo <14.1dev,>=14.0a
